build/classes/main/com/example/Abs$Companion.class
Compiled from "KotlinFile.kt"
public final class com.example.Abs$Companion {
  private com.example.Abs$Companion();
    Code:
       0: aload_0
       1: invokespecial #9                  // Method java/lang/Object."<init>":()V
       4: return
    LineNumberTable:
      line 206: 0
    LocalVariableTable:
      Start  Length  Slot  Name   Signature
          0       5     0  this   Lcom/example/Abs$Companion;

  public com.example.Abs$Companion(kotlin.jvm.internal.DefaultConstructorMarker);
    Code:
       0: aload_0
       1: invokespecial #13                 // Method "<init>":()V
       4: return
    LineNumberTable:
      line 206: 0
    LocalVariableTable:
      Start  Length  Slot  Name   Signature
          0       5     0  this   Lcom/example/Abs$Companion;
          0       5     1 $constructor_marker   Lkotlin/jvm/internal/DefaultConstructorMarker;
}

build/classes/main/com/example/Abs.class
Compiled from "KotlinFile.kt"
public abstract class com.example.Abs {
  public static final com.example.Abs$Companion Companion;

  public static void abs$annotations();
    Code:
       0: return

  public abstract int getAbs();

  public com.example.Abs();
    Code:
       0: aload_0
       1: invokespecial #14                 // Method java/lang/Object."<init>":()V
       4: return
    LineNumberTable:
      line 202: 0
    LocalVariableTable:
      Start  Length  Slot  Name   Signature
          0       5     0  this   Lcom/example/Abs;

  static {};
    Code:
       0: new           #32                 // class com/example/Abs$Companion
       3: dup
       4: aconst_null
       5: invokespecial #35                 // Method com/example/Abs$Companion."<init>":(Lkotlin/jvm/internal/DefaultConstructorMarker;)V
       8: putstatic     #37                 // Field Companion:Lcom/example/Abs$Companion;
      11: return
}

build/classes/main/com/example/annotations/ClassAnnotation.class
Compiled from "ClassAnnotation.kt"
public interface com.example.annotations.ClassAnnotation extends java.lang.annotation.Annotation {
}

build/classes/main/com/example/Ano.class
Compiled from "KotlinFile.kt"
public interface com.example.Ano extends java.lang.annotation.Annotation {
  public abstract java.lang.String name();
}

build/classes/main/com/example/Bool$Companion.class
Compiled from "KotlinFile.kt"
public final class com.example.Bool$Companion {
  public final java.util.List<com.example.Bool> list();
    Code:
       0: invokestatic  #14                 // Method com/example/Bool.values:()[Lcom/example/Bool;
       3: checkcast     #16                 // class "[Ljava/lang/Object;"
       6: invokestatic  #22                 // Method kotlin/collections/ArraysKt.toList:([Ljava/lang/Object;)Ljava/util/List;
       9: areturn
    LineNumberTable:
      line 187: 0
    LocalVariableTable:
      Start  Length  Slot  Name   Signature
          0      10     0  this   Lcom/example/Bool$Companion;

  private com.example.Bool$Companion();
    Code:
       0: aload_0
       1: invokespecial #28                 // Method java/lang/Object."<init>":()V
       4: return
    LineNumberTable:
      line 185: 0
    LocalVariableTable:
      Start  Length  Slot  Name   Signature
          0       5     0  this   Lcom/example/Bool$Companion;

  public com.example.Bool$Companion(kotlin.jvm.internal.DefaultConstructorMarker);
    Code:
       0: aload_0
       1: invokespecial #30                 // Method "<init>":()V
       4: return
    LineNumberTable:
      line 185: 0
    LocalVariableTable:
      Start  Length  Slot  Name   Signature
          0       5     0  this   Lcom/example/Bool$Companion;
          0       5     1 $constructor_marker   Lkotlin/jvm/internal/DefaultConstructorMarker;
}

build/classes/main/com/example/Bool$NG$Hero.class
Compiled from "KotlinFile.kt"
public final class com.example.Bool$NG$Hero {
  public com.example.Bool$NG$Hero();
    Code:
       0: aload_0
       1: invokespecial #9                  // Method java/lang/Object."<init>":()V
       4: return
    LineNumberTable:
      line 173: 0
    LocalVariableTable:
      Start  Length  Slot  Name   Signature
          0       5     0  this   Lcom/example/Bool$NG$Hero;
}

build/classes/main/com/example/Bool$NG.class
Compiled from "KotlinFile.kt"
public final class com.example.Bool$NG extends com.example.Bool {
  private final int int;

  public static void int$annotations();
    Code:
       0: return

  public int getInt();
    Code:
       0: aload_0
       1: getfield      #14                 // Field int:I
       4: ireturn
    LineNumberTable:
      line 172: 0
    LocalVariableTable:
      Start  Length  Slot  Name   Signature
          0       5     0  this   Lcom/example/Bool$NG;

  com.example.Bool$NG();
    Code:
       0: aload_0
       1: aload_1
       2: iload_2
       3: iconst_0
       4: invokespecial #21                 // Method com/example/Bool."<init>":(Ljava/lang/String;IZ)V
       7: return
    LineNumberTable:
      line 171: 0
      line 171: 4
    LocalVariableTable:
      Start  Length  Slot  Name   Signature
          0       8     0  this   Lcom/example/Bool$NG;
          0       8     1 $enum_name_or_ordinal$0   Ljava/lang/String;
          0       8     2 $enum_name_or_ordinal$1   I
}

build/classes/main/com/example/Bool$OK$Child.class
Compiled from "KotlinFile.kt"
public final class com.example.Bool$OK$Child {
  public com.example.Bool$OK$Child();
    Code:
       0: aload_0
       1: invokespecial #9                  // Method java/lang/Object."<init>":()V
       4: return
    LineNumberTable:
      line 167: 0
    LocalVariableTable:
      Start  Length  Slot  Name   Signature
          0       5     0  this   Lcom/example/Bool$OK$Child;
}

build/classes/main/com/example/Bool$OK.class
Compiled from "KotlinFile.kt"
public final class com.example.Bool$OK extends com.example.Bool {
  private final int int;

  public static void int$annotations();
    Code:
       0: return

  public int getInt();
    Code:
       0: aload_0
       1: getfield      #14                 // Field int:I
       4: ireturn
    LineNumberTable:
      line 166: 0
    LocalVariableTable:
      Start  Length  Slot  Name   Signature
          0       5     0  this   Lcom/example/Bool$OK;

  com.example.Bool$OK();
    Code:
       0: aload_0
       1: aload_1
       2: iload_2
       3: iconst_1
       4: invokespecial #21                 // Method com/example/Bool."<init>":(Ljava/lang/String;IZ)V
       7: aload_0
       8: iconst_1
       9: putfield      #14                 // Field int:I
      12: return
    LineNumberTable:
      line 165: 0
      line 165: 4
      line 166: 7
    LocalVariableTable:
      Start  Length  Slot  Name   Signature
          0      13     0  this   Lcom/example/Bool$OK;
          0      13     1 $enum_name_or_ordinal$0   Ljava/lang/String;
          0      13     2 $enum_name_or_ordinal$1   I
}

build/classes/main/com/example/Bool.class
Compiled from "KotlinFile.kt"
public abstract class com.example.Bool extends java.lang.Enum<com.example.Bool> {
  public static final com.example.Bool OK;

  public static final com.example.Bool NG;

  private static final com.example.Bool[] $VALUES;

  private final boolean asBoolean;

  public static final com.example.Bool$Companion Companion;

  static {};
    Code:
       0: iconst_2
       1: anewarray     #2                  // class com/example/Bool
       4: dup
       5: dup
       6: iconst_0
       7: new           #91                 // class com/example/Bool$OK
      10: dup
      11: ldc           #92                 // String OK
      13: iconst_0
      14: invokespecial #93                 // Method com/example/Bool$OK."<init>":(Ljava/lang/String;I)V
      17: dup
      18: putstatic     #95                 // Field OK:Lcom/example/Bool;
      21: aastore
      22: dup
      23: iconst_1
      24: new           #97                 // class com/example/Bool$NG
      27: dup
      28: ldc           #98                 // String NG
      30: iconst_1
      31: invokespecial #99                 // Method com/example/Bool$NG."<init>":(Ljava/lang/String;I)V
      34: dup
      35: putstatic     #101                // Field NG:Lcom/example/Bool;
      38: aastore
      39: putstatic     #66                 // Field $VALUES:[Lcom/example/Bool;
      42: new           #103                // class com/example/Bool$Companion
      45: dup
      46: aconst_null
      47: invokespecial #106                // Method com/example/Bool$Companion."<init>":(Lkotlin/jvm/internal/DefaultConstructorMarker;)V
      50: putstatic     #108                // Field Companion:Lcom/example/Bool$Companion;
      53: return

  public static void int$annotations();
    Code:
       0: return

  public abstract int getInt();

  public final int size(com.example.Vip);
    Code:
       0: aload_1
       1: ldc           #22                 // String $receiver
       3: invokestatic  #28                 // Method kotlin/jvm/internal/Intrinsics.checkParameterIsNotNull:(Ljava/lang/Object;Ljava/lang/String;)V
       6: bipush        10
       8: ireturn
    LineNumberTable:
      line 179: 6
    LocalVariableTable:
      Start  Length  Slot  Name   Signature
          0       9     0  this   Lcom/example/Bool;
          0       9     1 $receiver   Lcom/example/Vip;

  public static void size$annotations(com.example.Ano);
    Code:
       0: return

  public final int getSize(com.example.Ano);
    Code:
       0: aload_1
       1: ldc           #22                 // String $receiver
       3: invokestatic  #28                 // Method kotlin/jvm/internal/Intrinsics.checkParameterIsNotNull:(Ljava/lang/Object;Ljava/lang/String;)V
       6: aload_1
       7: invokeinterface #39,  1           // InterfaceMethod com/example/Ano.name:()Ljava/lang/String;
      12: invokevirtual #44                 // Method java/lang/String.length:()I
      15: ireturn
    LineNumberTable:
      line 183: 6
    LocalVariableTable:
      Start  Length  Slot  Name   Signature
          0      16     0  this   Lcom/example/Bool;
          0      16     1 $receiver   Lcom/example/Ano;

  public final boolean getAsBoolean();
    Code:
       0: aload_0
       1: getfield      #51                 // Field asBoolean:Z
       4: ireturn
    LineNumberTable:
      line 163: 0
    LocalVariableTable:
      Start  Length  Slot  Name   Signature
          0       5     0  this   Lcom/example/Bool;

  protected com.example.Bool(boolean);
    Code:
       0: aload_0
       1: aload_1
       2: iload_2
       3: invokespecial #56                 // Method java/lang/Enum."<init>":(Ljava/lang/String;I)V
       6: aload_0
       7: iload_3
       8: putfield      #51                 // Field asBoolean:Z
      11: return
    LineNumberTable:
      line 163: 0
    LocalVariableTable:
      Start  Length  Slot  Name   Signature
          0      12     0  this   Lcom/example/Bool;
          0      12     1 $enum_name_or_ordinal$0   Ljava/lang/String;
          0      12     2 $enum_name_or_ordinal$1   I
          0      12     3 asBoolean   Z

  public static com.example.Bool[] values();
    Code:
       0: getstatic     #66                 // Field $VALUES:[Lcom/example/Bool;
       3: invokevirtual #71                 // Method "[Lcom/example/Bool;".clone:()Ljava/lang/Object;
       6: checkcast     #67                 // class "[Lcom/example/Bool;"
       9: areturn

  public static com.example.Bool valueOf(java.lang.String);
    Code:
       0: ldc           #2                  // class com/example/Bool
       2: aload_0
       3: invokestatic  #76                 // Method java/lang/Enum.valueOf:(Ljava/lang/Class;Ljava/lang/String;)Ljava/lang/Enum;
       6: checkcast     #2                  // class com/example/Bool
       9: areturn
}

build/classes/main/com/example/Bounds.class
Compiled from "KotlinFile.kt"
public final class com.example.Bounds extends java.lang.Enum<com.example.Bounds> {
  public static final com.example.Bounds MAX;

  public static final com.example.Bounds MIN;

  private static final com.example.Bounds[] $VALUES;

  private final int asInt;

  static {};
    Code:
       0: iconst_2
       1: anewarray     #2                  // class com/example/Bounds
       4: dup
       5: dup
       6: iconst_0
       7: new           #2                  // class com/example/Bounds
      10: dup
      11: ldc           #57                 // String MAX
      13: iconst_0
      14: iconst_1
      15: invokespecial #59                 // Method "<init>":(Ljava/lang/String;II)V
      18: dup
      19: putstatic     #61                 // Field MAX:Lcom/example/Bounds;
      22: aastore
      23: dup
      24: iconst_1
      25: new           #2                  // class com/example/Bounds
      28: dup
      29: ldc           #62                 // String MIN
      31: iconst_1
      32: iconst_0
      33: invokespecial #59                 // Method "<init>":(Ljava/lang/String;II)V
      36: dup
      37: putstatic     #64                 // Field MIN:Lcom/example/Bounds;
      40: aastore
      41: putstatic     #34                 // Field $VALUES:[Lcom/example/Bounds;
      44: return
    LineNumberTable:
      line 211: 15

  public final int reverse();
    Code:
       0: aload_0
       1: getfield      #19                 // Field asInt:I
       4: ineg
       5: ireturn
    LineNumberTable:
      line 212: 0
    LocalVariableTable:
      Start  Length  Slot  Name   Signature
          0       6     0  this   Lcom/example/Bounds;

  public final int ord();
    Code:
       0: aload_0
       1: getfield      #19                 // Field asInt:I
       4: ireturn
    LineNumberTable:
      line 213: 0
    LocalVariableTable:
      Start  Length  Slot  Name   Signature
          0       5     0  this   Lcom/example/Bounds;

  public final int getAsInt();
    Code:
       0: aload_0
       1: getfield      #19                 // Field asInt:I
       4: ireturn
    LineNumberTable:
      line 210: 0
    LocalVariableTable:
      Start  Length  Slot  Name   Signature
          0       5     0  this   Lcom/example/Bounds;

  protected com.example.Bounds(int);
    Code:
       0: aload_0
       1: aload_1
       2: iload_2
       3: invokespecial #27                 // Method java/lang/Enum."<init>":(Ljava/lang/String;I)V
       6: aload_0
       7: iload_3
       8: putfield      #19                 // Field asInt:I
      11: return
    LineNumberTable:
      line 210: 0
    LocalVariableTable:
      Start  Length  Slot  Name   Signature
          0      12     0  this   Lcom/example/Bounds;
          0      12     1 $enum_name_or_ordinal$0   Ljava/lang/String;
          0      12     2 $enum_name_or_ordinal$1   I
          0      12     3 asInt   I

  public static com.example.Bounds[] values();
    Code:
       0: getstatic     #34                 // Field $VALUES:[Lcom/example/Bounds;
       3: invokevirtual #39                 // Method "[Lcom/example/Bounds;".clone:()Ljava/lang/Object;
       6: checkcast     #35                 // class "[Lcom/example/Bounds;"
       9: areturn

  public static com.example.Bounds valueOf(java.lang.String);
    Code:
       0: ldc           #2                  // class com/example/Bounds
       2: aload_0
       3: invokestatic  #44                 // Method java/lang/Enum.valueOf:(Ljava/lang/Class;Ljava/lang/String;)Ljava/lang/Enum;
       6: checkcast     #2                  // class com/example/Bounds
       9: areturn
}

build/classes/main/com/example/Data.class
Compiled from "KotlinFile.kt"
public final class com.example.Data<T> {
  private final T value;

  public final T getValue();
    Code:
       0: aload_0
       1: getfield      #14                 // Field value:Ljava/lang/Object;
       4: areturn
    LineNumberTable:
      line 128: 0
    LocalVariableTable:
      Start  Length  Slot  Name   Signature
          0       5     0  this   Lcom/example/Data;

  public com.example.Data(T);
    Code:
       0: aload_1
       1: ldc           #19                 // String value
       3: invokestatic  #25                 // Method kotlin/jvm/internal/Intrinsics.checkParameterIsNotNull:(Ljava/lang/Object;Ljava/lang/String;)V
       6: aload_0
       7: invokespecial #28                 // Method java/lang/Object."<init>":()V
      10: aload_0
      11: aload_1
      12: putfield      #14                 // Field value:Ljava/lang/Object;
      15: return
    LineNumberTable:
      line 128: 6
    LocalVariableTable:
      Start  Length  Slot  Name   Signature
          0      16     0  this   Lcom/example/Data;
          0      16     1 value   Ljava/lang/Object;

  public final T component1();
    Code:
       0: aload_0
       1: getfield      #14                 // Field value:Ljava/lang/Object;
       4: areturn
    LocalVariableTable:
      Start  Length  Slot  Name   Signature
          0       5     0  this   Lcom/example/Data;

  public final com.example.Data<T> copy(T);
    Code:
       0: aload_1
       1: ldc           #19                 // String value
       3: invokestatic  #25                 // Method kotlin/jvm/internal/Intrinsics.checkParameterIsNotNull:(Ljava/lang/Object;Ljava/lang/String;)V
       6: new           #2                  // class com/example/Data
       9: dup
      10: aload_1
      11: invokespecial #33                 // Method "<init>":(Ljava/lang/Object;)V
      14: areturn
    LocalVariableTable:
      Start  Length  Slot  Name   Signature
          0      15     0  this   Lcom/example/Data;
          0      15     1 value   Ljava/lang/Object;

  public static com.example.Data copy$default(com.example.Data, java.lang.Object, int, java.lang.Object);
    Code:
       0: iload_2
       1: iconst_1
       2: iand
       3: ifeq          11
       6: aload_0
       7: getfield      #14                 // Field value:Ljava/lang/Object;
      10: astore_1
      11: aload_0
      12: aload_1
      13: invokevirtual #37                 // Method copy:(Ljava/lang/Object;)Lcom/example/Data;
      16: areturn

  public java.lang.String toString();
    Code:
       0: new           #41                 // class java/lang/StringBuilder
       3: dup
       4: invokespecial #42                 // Method java/lang/StringBuilder."<init>":()V
       7: ldc           #44                 // String Data(value=
       9: invokevirtual #48                 // Method java/lang/StringBuilder.append:(Ljava/lang/String;)Ljava/lang/StringBuilder;
      12: aload_0
      13: getfield      #14                 // Field value:Ljava/lang/Object;
      16: invokevirtual #51                 // Method java/lang/StringBuilder.append:(Ljava/lang/Object;)Ljava/lang/StringBuilder;
      19: ldc           #53                 // String )
      21: invokevirtual #48                 // Method java/lang/StringBuilder.append:(Ljava/lang/String;)Ljava/lang/StringBuilder;
      24: invokevirtual #55                 // Method java/lang/StringBuilder.toString:()Ljava/lang/String;
      27: areturn

  public int hashCode();
    Code:
       0: aload_0
       1: getfield      #14                 // Field value:Ljava/lang/Object;
       4: dup
       5: ifnull        14
       8: invokevirtual #59                 // Method java/lang/Object.hashCode:()I
      11: goto          16
      14: pop
      15: iconst_0
      16: ireturn

  public boolean equals(java.lang.Object);
    Code:
       0: aload_0
       1: aload_1
       2: if_acmpeq     31
       5: aload_1
       6: instanceof    #2                  // class com/example/Data
       9: ifeq          33
      12: aload_1
      13: checkcast     #2                  // class com/example/Data
      16: astore_2
      17: aload_0
      18: getfield      #14                 // Field value:Ljava/lang/Object;
      21: aload_2
      22: getfield      #14                 // Field value:Ljava/lang/Object;
      25: invokestatic  #65                 // Method kotlin/jvm/internal/Intrinsics.areEqual:(Ljava/lang/Object;Ljava/lang/Object;)Z
      28: ifeq          33
      31: iconst_1
      32: ireturn
      33: iconst_0
      34: ireturn
}

build/classes/main/com/example/Final.class
Compiled from "KotlinFile.kt"
public final class com.example.Final extends com.example.Sealed {
  public com.example.Final();
    Code:
       0: aload_0
       1: aconst_null
       2: invokespecial #10                 // Method com/example/Sealed."<init>":(Lkotlin/jvm/internal/DefaultConstructorMarker;)V
       5: return
    LineNumberTable:
      line 199: 0
      line 199: 2
    LocalVariableTable:
      Start  Length  Slot  Name   Signature
          0       6     0  this   Lcom/example/Final;
}

build/classes/main/com/example/Garply$Child.class
Compiled from "KotlinFile.kt"
public final class com.example.Garply$Child {
  public com.example.Garply$Child();
    Code:
       0: aload_0
       1: invokespecial #9                  // Method java/lang/Object."<init>":()V
       4: return
    LineNumberTable:
      line 115: 0
    LocalVariableTable:
      Start  Length  Slot  Name   Signature
          0       5     0  this   Lcom/example/Garply$Child;
}

build/classes/main/com/example/Garply$Companion$Child.class
Compiled from "KotlinFile.kt"
public final class com.example.Garply$Companion$Child {
  public com.example.Garply$Companion$Child();
    Code:
       0: aload_0
       1: invokespecial #8                  // Method java/lang/Object."<init>":()V
       4: return
    LineNumberTable:
      line 112: 0
    LocalVariableTable:
      Start  Length  Slot  Name   Signature
          0       5     0  this   Lcom/example/Garply$Companion$Child;
}

build/classes/main/com/example/Garply$Companion.class
Compiled from "KotlinFile.kt"
public final class com.example.Garply$Companion implements com.example.Garply {
  private static final java.lang.String waldo;

  public static void waldo$annotations();
    Code:
       0: return

  public java.lang.String getWaldo();
    Code:
       0: getstatic     #17                 // Field waldo:Ljava/lang/String;
       3: areturn
    LineNumberTable:
      line 111: 0
    LocalVariableTable:
      Start  Length  Slot  Name   Signature
          0       4     0  this   Lcom/example/Garply$Companion;

  private com.example.Garply$Companion();
    Code:
       0: aload_0
       1: invokespecial #22                 // Method java/lang/Object."<init>":()V
       4: ldc           #10                 // String waldo
       6: putstatic     #17                 // Field waldo:Ljava/lang/String;
       9: return
    LineNumberTable:
      line 109: 0
      line 111: 4
    LocalVariableTable:
      Start  Length  Slot  Name   Signature
          0      10     0  this   Lcom/example/Garply$Companion;

  public com.example.Quux lorem(com.example.Qux);
    Code:
       0: aload_1
       1: ldc           #26                 // String q
       3: invokestatic  #32                 // Method kotlin/jvm/internal/Intrinsics.checkParameterIsNotNull:(Ljava/lang/Object;Ljava/lang/String;)V
       6: aload_0
       7: aload_1
       8: invokestatic  #37                 // Method com/example/Garply$DefaultImpls.lorem:(Lcom/example/Garply;Lcom/example/Qux;)Lcom/example/Quux;
      11: areturn
    LineNumberTable:
      line 109: 6
    LocalVariableTable:
      Start  Length  Slot  Name   Signature
          0      12     0  this   Lcom/example/Garply;
          0      12     1     q   Lcom/example/Qux;

  public int getDp();
    Code:
       0: aload_0
       1: invokestatic  #44                 // Method com/example/Garply$DefaultImpls.getDp:(Lcom/example/Garply;)I
       4: ireturn
    LineNumberTable:
      line 109: 0
    LocalVariableTable:
      Start  Length  Slot  Name   Signature
          0       5     0  this   Lcom/example/Garply;

  public com.example.Garply$Companion(kotlin.jvm.internal.DefaultConstructorMarker);
    Code:
       0: aload_0
       1: invokespecial #46                 // Method "<init>":()V
       4: return
    LineNumberTable:
      line 109: 0
    LocalVariableTable:
      Start  Length  Slot  Name   Signature
          0       5     0  this   Lcom/example/Garply$Companion;
          0       5     1 $constructor_marker   Lkotlin/jvm/internal/DefaultConstructorMarker;
}

build/classes/main/com/example/Garply$DefaultImpls.class
Compiled from "KotlinFile.kt"
public final class com.example.Garply$DefaultImpls {
  public static void waldo$annotations();
    Code:
       0: return

  public static com.example.Quux lorem(com.example.Garply, com.example.Qux);
    Code:
       0: aload_1
       1: ldc           #12                 // String q
       3: invokestatic  #18                 // Method kotlin/jvm/internal/Intrinsics.checkParameterIsNotNull:(Ljava/lang/Object;Ljava/lang/String;)V
       6: new           #20                 // class com/example/Quux
       9: dup
      10: aload_1
      11: invokevirtual #26                 // Method com/example/Qux.getProp:()Ljava/lang/String;
      14: invokespecial #30                 // Method com/example/Quux."<init>":(Ljava/lang/String;)V
      17: areturn
    LineNumberTable:
      line 103: 6
    LocalVariableTable:
      Start  Length  Slot  Name   Signature
          0      18     0 $this   Lcom/example/Garply;
          0      18     1     q   Lcom/example/Qux;

  public static void dp$annotations();
    Code:
       0: return

  public static int getDp(com.example.Garply);
    Code:
       0: iconst_1
       1: ireturn
    LineNumberTable:
      line 107: 0
    LocalVariableTable:
      Start  Length  Slot  Name   Signature
          0       2     0 $this   Lcom/example/Garply;
}

build/classes/main/com/example/Garply.class
Compiled from "KotlinFile.kt"
public interface com.example.Garply {
  public static final com.example.Garply$Companion Companion;

  public abstract java.lang.String getWaldo();

  public abstract com.example.Quux lorem(com.example.Qux);

  public abstract int getDp();

  static {};
    Code:
       0: new           #40                 // class com/example/Garply$Companion
       3: dup
       4: aconst_null
       5: invokespecial #44                 // Method com/example/Garply$Companion."<init>":(Lkotlin/jvm/internal/DefaultConstructorMarker;)V
       8: putstatic     #46                 // Field Companion:Lcom/example/Garply$Companion;
      11: return
}

build/classes/main/com/example/Impl.class
Compiled from "KotlinFile.kt"
public final class com.example.Impl implements com.example.Garply {
  private final java.lang.String waldo;

  public java.lang.String getWaldo();
    Code:
       0: aload_0
       1: getfield      #14                 // Field waldo:Ljava/lang/String;
       4: areturn
    LineNumberTable:
      line 125: 0
    LocalVariableTable:
      Start  Length  Slot  Name   Signature
          0       5     0  this   Lcom/example/Impl;

  public com.example.Impl(java.lang.String);
    Code:
       0: aload_1
       1: ldc           #19                 // String waldo
       3: invokestatic  #25                 // Method kotlin/jvm/internal/Intrinsics.checkParameterIsNotNull:(Ljava/lang/Object;Ljava/lang/String;)V
       6: aload_0
       7: invokespecial #28                 // Method java/lang/Object."<init>":()V
      10: aload_0
      11: aload_1
      12: putfield      #14                 // Field waldo:Ljava/lang/String;
      15: return
    LineNumberTable:
      line 125: 6
    LocalVariableTable:
      Start  Length  Slot  Name   Signature
          0      16     0  this   Lcom/example/Impl;
          0      16     1 waldo   Ljava/lang/String;

  public com.example.Quux lorem(com.example.Qux);
    Code:
       0: aload_1
       1: ldc           #32                 // String q
       3: invokestatic  #25                 // Method kotlin/jvm/internal/Intrinsics.checkParameterIsNotNull:(Ljava/lang/Object;Ljava/lang/String;)V
       6: aload_0
       7: aload_1
       8: invokestatic  #37                 // Method com/example/Garply$DefaultImpls.lorem:(Lcom/example/Garply;Lcom/example/Qux;)Lcom/example/Quux;
      11: areturn
    LineNumberTable:
      line 125: 6
    LocalVariableTable:
      Start  Length  Slot  Name   Signature
          0      12     0  this   Lcom/example/Garply;
          0      12     1     q   Lcom/example/Qux;

  public int getDp();
    Code:
       0: aload_0
       1: invokestatic  #44                 // Method com/example/Garply$DefaultImpls.getDp:(Lcom/example/Garply;)I
       4: ireturn
    LineNumberTable:
      line 125: 0
    LocalVariableTable:
      Start  Length  Slot  Name   Signature
          0       5     0  this   Lcom/example/Garply;

  public final java.lang.String component1();
    Code:
       0: aload_0
       1: invokevirtual #47                 // Method getWaldo:()Ljava/lang/String;
       4: areturn
    LocalVariableTable:
      Start  Length  Slot  Name   Signature
          0       5     0  this   Lcom/example/Impl;

  public final com.example.Impl copy(java.lang.String);
    Code:
       0: aload_1
       1: ldc           #19                 // String waldo
       3: invokestatic  #25                 // Method kotlin/jvm/internal/Intrinsics.checkParameterIsNotNull:(Ljava/lang/Object;Ljava/lang/String;)V
       6: new           #2                  // class com/example/Impl
       9: dup
      10: aload_1
      11: invokespecial #51                 // Method "<init>":(Ljava/lang/String;)V
      14: areturn
    LocalVariableTable:
      Start  Length  Slot  Name   Signature
          0      15     0  this   Lcom/example/Impl;
          0      15     1 waldo   Ljava/lang/String;

  public static com.example.Impl copy$default(com.example.Impl, java.lang.String, int, java.lang.Object);
    Code:
       0: iload_2
       1: iconst_1
       2: iand
       3: ifeq          11
       6: aload_0
       7: invokevirtual #47                 // Method getWaldo:()Ljava/lang/String;
      10: astore_1
      11: aload_0
      12: aload_1
      13: invokevirtual #55                 // Method copy:(Ljava/lang/String;)Lcom/example/Impl;
      16: areturn

  public java.lang.String toString();
    Code:
       0: new           #58                 // class java/lang/StringBuilder
       3: dup
       4: invokespecial #59                 // Method java/lang/StringBuilder."<init>":()V
       7: ldc           #61                 // String Impl(waldo=
       9: invokevirtual #65                 // Method java/lang/StringBuilder.append:(Ljava/lang/String;)Ljava/lang/StringBuilder;
      12: aload_0
      13: invokevirtual #47                 // Method getWaldo:()Ljava/lang/String;
      16: invokevirtual #65                 // Method java/lang/StringBuilder.append:(Ljava/lang/String;)Ljava/lang/StringBuilder;
      19: ldc           #67                 // String )
      21: invokevirtual #65                 // Method java/lang/StringBuilder.append:(Ljava/lang/String;)Ljava/lang/StringBuilder;
      24: invokevirtual #69                 // Method java/lang/StringBuilder.toString:()Ljava/lang/String;
      27: areturn

  public int hashCode();
    Code:
       0: aload_0
       1: invokevirtual #47                 // Method getWaldo:()Ljava/lang/String;
       4: dup
       5: ifnull        14
       8: invokevirtual #72                 // Method java/lang/Object.hashCode:()I
      11: goto          16
      14: pop
      15: iconst_0
      16: ireturn

  public boolean equals(java.lang.Object);
    Code:
       0: aload_0
       1: aload_1
       2: if_acmpeq     31
       5: aload_1
       6: instanceof    #2                  // class com/example/Impl
       9: ifeq          33
      12: aload_1
      13: checkcast     #2                  // class com/example/Impl
      16: astore_2
      17: aload_0
      18: invokevirtual #47                 // Method getWaldo:()Ljava/lang/String;
      21: aload_2
      22: invokevirtual #47                 // Method getWaldo:()Ljava/lang/String;
      25: invokestatic  #80                 // Method kotlin/jvm/internal/Intrinsics.areEqual:(Ljava/lang/Object;Ljava/lang/Object;)Z
      28: ifeq          33
      31: iconst_1
      32: ireturn
      33: iconst_0
      34: ireturn
}

build/classes/main/com/example/IsIt$InstanceInner.class
Compiled from "IsIt.java"
public class com.example.IsIt$InstanceInner {
  final com.example.IsIt this$0;

  public com.example.IsIt$InstanceInner(com.example.IsIt);
    Code:
       0: aload_0
       1: aload_1
       2: putfield      #1                  // Field this$0:Lcom/example/IsIt;
       5: aload_0
       6: invokespecial #2                  // Method java/lang/Object."<init>":()V
       9: return
    LineNumberTable:
      line 24: 0
    LocalVariableTable:
      Start  Length  Slot  Name   Signature
          0      10     0  this   Lcom/example/IsIt$InstanceInner;
          0      10     1 this$0   Lcom/example/IsIt;
}

build/classes/main/com/example/IsIt$StaticInner.class
Compiled from "IsIt.java"
public class com.example.IsIt$StaticInner {
  public com.example.IsIt$StaticInner();
    Code:
       0: aload_0
       1: invokespecial #1                  // Method java/lang/Object."<init>":()V
       4: return
    LineNumberTable:
      line 21: 0
    LocalVariableTable:
      Start  Length  Slot  Name   Signature
          0       5     0  this   Lcom/example/IsIt$StaticInner;

  static void call();
    Code:
       0: return
    LineNumberTable:
      line 22: 0
}

build/classes/main/com/example/IsIt.class
Compiled from "IsIt.java"
public class com.example.IsIt {
  public com.example.IsIt();
    Code:
       0: aload_0
       1: invokespecial #1                  // Method java/lang/Object."<init>":()V
       4: return
    LineNumberTable:
      line 18: 0
    LocalVariableTable:
      Start  Length  Slot  Name   Signature
          0       5     0  this   Lcom/example/IsIt;

  static void call();
    Code:
       0: return
    LineNumberTable:
      line 19: 0
}

build/classes/main/com/example/KotlinClasses$garply$1.class
Compiled from "KotlinFile.kt"
public final class com.example.KotlinClasses$garply$1 implements com.example.Garply {
  public static void waldo$annotations();
    Code:
       0: return

  public java.lang.String getWaldo();
    Code:
       0: ldc           #16                 // String waldo
       2: areturn
    LineNumberTable:
      line 121: 0
    LocalVariableTable:
      Start  Length  Slot  Name   Signature
          0       3     0  this   Lcom/example/KotlinClasses$garply$1;

  com.example.KotlinClasses$garply$1();
    Code:
       0: aload_0
       1: invokespecial #21                 // Method java/lang/Object."<init>":()V
       4: return
    LineNumberTable:
      line 119: 0
    LocalVariableTable:
      Start  Length  Slot  Name   Signature
          0       5     0  this   Lcom/example/KotlinClasses$garply$1;

  public com.example.Quux lorem(com.example.Qux);
    Code:
       0: aload_1
       1: ldc           #25                 // String q
       3: invokestatic  #31                 // Method kotlin/jvm/internal/Intrinsics.checkParameterIsNotNull:(Ljava/lang/Object;Ljava/lang/String;)V
       6: aload_0
       7: aload_1
       8: invokestatic  #36                 // Method com/example/Garply$DefaultImpls.lorem:(Lcom/example/Garply;Lcom/example/Qux;)Lcom/example/Quux;
      11: areturn
    LineNumberTable:
      line 119: 6
    LocalVariableTable:
      Start  Length  Slot  Name   Signature
          0      12     0  this   Lcom/example/Garply;
          0      12     1     q   Lcom/example/Qux;

  public int getDp();
    Code:
       0: aload_0
       1: invokestatic  #43                 // Method com/example/Garply$DefaultImpls.getDp:(Lcom/example/Garply;)I
       4: ireturn
    LineNumberTable:
      line 119: 0
    LocalVariableTable:
      Start  Length  Slot  Name   Signature
          0       5     0  this   Lcom/example/Garply;
}

build/classes/main/com/example/KotlinClasses.class
Compiled from "KotlinFile.kt"
public final class com.example.KotlinClasses {
  private static final int baz;

  private static final com.example.Garply garply;

  public static final java.lang.String foo(java.lang.String);
    Code:
       0: aload_0
       1: ldc           #13                 // String bar
       3: invokestatic  #19                 // Method kotlin/jvm/internal/Intrinsics.checkParameterIsNotNull:(Ljava/lang/Object;Ljava/lang/String;)V
       6: aload_0
       7: astore_1
       8: aload_1
       9: invokevirtual #25                 // Method java/lang/String.toUpperCase:()Ljava/lang/String;
      12: dup
      13: ldc           #27                 // String (this as java.lang.String).toUpperCase()
      15: invokestatic  #30                 // Method kotlin/jvm/internal/Intrinsics.checkExpressionValueIsNotNull:(Ljava/lang/Object;Ljava/lang/String;)V
      18: areturn
    LineNumberTable:
      line 24: 6
      line 24: 18
    LocalVariableTable:
      Start  Length  Slot  Name   Signature
          0      19     0   bar   Ljava/lang/String;

  public static void baz$annotations();
    Code:
       0: return

  public static final int getBaz();
    Code:
       0: getstatic     #39                 // Field baz:I
       3: ireturn
    LineNumberTable:
      line 26: 0

  public static void garply$annotations();
    Code:
       0: return

  public static final com.example.Garply getGarply();
    Code:
       0: getstatic     #46                 // Field garply:Lcom/example/Garply;
       3: areturn
    LineNumberTable:
      line 119: 0

  static {};
    Code:
       0: ldc           #61                 // String baz
       2: invokestatic  #63                 // Method foo:(Ljava/lang/String;)Ljava/lang/String;
       5: invokevirtual #66                 // Method java/lang/String.length:()I
       8: putstatic     #39                 // Field baz:I
      11: new           #68                 // class com/example/KotlinClasses$garply$1
      14: dup
      15: invokespecial #71                 // Method com/example/KotlinClasses$garply$1."<init>":()V
      18: checkcast     #73                 // class com/example/Garply
      21: putstatic     #46                 // Field garply:Lcom/example/Garply;
      24: return
    LineNumberTable:
      line 26: 0
      line 119: 11
}

build/classes/main/com/example/Open$In.class
Compiled from "KotlinFile.kt"
public final class com.example.Open$In {
  final com.example.Open this$0;

  public final T value();
    Code:
       0: aload_0
       1: getfield      #11                 // Field this$0:Lcom/example/Open;
       4: invokevirtual #16                 // Method com/example/Open.getValue:()Ljava/lang/Object;
       7: areturn
    LineNumberTable:
      line 134: 0
    LocalVariableTable:
      Start  Length  Slot  Name   Signature
          0       8     0  this   Lcom/example/Open$In;

  public com.example.Open$In();
    Code:
       0: aload_0
       1: aload_1
       2: putfield      #11                 // Field this$0:Lcom/example/Open;
       5: aload_0
       6: invokespecial #23                 // Method java/lang/Object."<init>":()V
       9: return
    LineNumberTable:
      line 133: 0
    LocalVariableTable:
      Start  Length  Slot  Name   Signature
          0      10     0  this   Lcom/example/Open$In;
          0      10     1 $outer   Lcom/example/Open;
}

build/classes/main/com/example/Open.class
Compiled from "KotlinFile.kt"
public class com.example.Open<T> {
  private final T value;

  public final T value();
    Code:
       0: aload_0
       1: getfield      #12                 // Field value:Ljava/lang/Object;
       4: areturn
    LineNumberTable:
      line 132: 0
    LocalVariableTable:
      Start  Length  Slot  Name   Signature
          0       5     0  this   Lcom/example/Open;

  public final T getValue();
    Code:
       0: aload_0
       1: getfield      #12                 // Field value:Ljava/lang/Object;
       4: areturn
    LineNumberTable:
      line 131: 0
    LocalVariableTable:
      Start  Length  Slot  Name   Signature
          0       5     0  this   Lcom/example/Open;

  public com.example.Open(T);
    Code:
       0: aload_1
       1: ldc           #19                 // String value
       3: invokestatic  #25                 // Method kotlin/jvm/internal/Intrinsics.checkParameterIsNotNull:(Ljava/lang/Object;Ljava/lang/String;)V
       6: aload_0
       7: invokespecial #28                 // Method java/lang/Object."<init>":()V
      10: aload_0
      11: aload_1
      12: putfield      #12                 // Field value:Ljava/lang/Object;
      15: return
    LineNumberTable:
      line 131: 6
    LocalVariableTable:
      Start  Length  Slot  Name   Signature
          0      16     0  this   Lcom/example/Open;
          0      16     1 value   Ljava/lang/Object;
}

build/classes/main/com/example/Ord$Child.class
Compiled from "KotlinFile.kt"
public final class com.example.Ord$Child {
  public com.example.Ord$Child();
    Code:
       0: aload_0
       1: invokespecial #8                  // Method java/lang/Object."<init>":()V
       4: return
    LineNumberTable:
      line 159: 0
    LocalVariableTable:
      Start  Length  Slot  Name   Signature
          0       5     0  this   Lcom/example/Ord$Child;
}

build/classes/main/com/example/Ord.class
Compiled from "KotlinFile.kt"
public final class com.example.Ord extends java.lang.Enum<com.example.Ord> {
  public static final com.example.Ord LT;

  public static final com.example.Ord EQ;

  public static final com.example.Ord GT;

  private static final com.example.Ord[] $VALUES;

  static {};
    Code:
       0: iconst_3
       1: anewarray     #2                  // class com/example/Ord
       4: dup
       5: dup
       6: iconst_0
       7: new           #2                  // class com/example/Ord
      10: dup
      11: ldc           #51                 // String LT
      13: iconst_0
      14: invokespecial #52                 // Method "<init>":(Ljava/lang/String;I)V
      17: dup
      18: putstatic     #54                 // Field LT:Lcom/example/Ord;
      21: aastore
      22: dup
      23: iconst_1
      24: new           #2                  // class com/example/Ord
      27: dup
      28: ldc           #55                 // String EQ
      30: iconst_1
      31: invokespecial #52                 // Method "<init>":(Ljava/lang/String;I)V
      34: dup
      35: putstatic     #57                 // Field EQ:Lcom/example/Ord;
      38: aastore
      39: dup
      40: iconst_2
      41: new           #2                  // class com/example/Ord
      44: dup
      45: ldc           #58                 // String GT
      47: iconst_2
      48: invokespecial #52                 // Method "<init>":(Ljava/lang/String;I)V
      51: dup
      52: putstatic     #60                 // Field GT:Lcom/example/Ord;
      55: aastore
      56: putstatic     #27                 // Field $VALUES:[Lcom/example/Ord;
      59: return

  protected com.example.Ord();
    Code:
       0: aload_0
       1: aload_1
       2: iload_2
       3: invokespecial #18                 // Method java/lang/Enum."<init>":(Ljava/lang/String;I)V
       6: return
    LineNumberTable:
      line 152: 0
    LocalVariableTable:
      Start  Length  Slot  Name   Signature
          0       7     0  this   Lcom/example/Ord;
          0       7     1 $enum_name_or_ordinal$0   Ljava/lang/String;
          0       7     2 $enum_name_or_ordinal$1   I

  public static com.example.Ord[] values();
    Code:
       0: getstatic     #27                 // Field $VALUES:[Lcom/example/Ord;
       3: invokevirtual #32                 // Method "[Lcom/example/Ord;".clone:()Ljava/lang/Object;
       6: checkcast     #28                 // class "[Lcom/example/Ord;"
       9: areturn

  public static com.example.Ord valueOf(java.lang.String);
    Code:
       0: ldc           #2                  // class com/example/Ord
       2: aload_0
       3: invokestatic  #37                 // Method java/lang/Enum.valueOf:(Ljava/lang/Class;Ljava/lang/String;)Ljava/lang/Enum;
       6: checkcast     #2                  // class com/example/Ord
       9: areturn
}

build/classes/main/com/example/Quux$createInner$ThisIsNotAlsoInner.class
Compiled from "KotlinFile.kt"
public final class com.example.Quux$createInner$ThisIsNotAlsoInner {
  public com.example.Quux$createInner$ThisIsNotAlsoInner();
    Code:
       0: aload_0
       1: invokespecial #14                 // Method java/lang/Object."<init>":()V
       4: return
    LineNumberTable:
      line 93: 0
    LocalVariableTable:
      Start  Length  Slot  Name   Signature
          0       5     0  this   Lcom/example/Quux$createInner$ThisIsNotAlsoInner;
}

build/classes/main/com/example/Quux$NotInner.class
Compiled from "KotlinFile.kt"
public final class com.example.Quux$NotInner {
  public com.example.Quux$NotInner();
    Code:
       0: aload_0
       1: invokespecial #9                  // Method java/lang/Object."<init>":()V
       4: return
    LineNumberTable:
      line 89: 0
    LocalVariableTable:
      Start  Length  Slot  Name   Signature
          0       5     0  this   Lcom/example/Quux$NotInner;
}

build/classes/main/com/example/Quux.class
Compiled from "KotlinFile.kt"
public final class com.example.Quux {
  private final java.lang.String name;

  public final java.lang.Object createInner();
    Code:
       0: new           #10                 // class com/example/Quux$createInner$ThisIsNotAlsoInner
       3: dup
       4: invokespecial #14                 // Method com/example/Quux$createInner$ThisIsNotAlsoInner."<init>":()V
       7: areturn
    LineNumberTable:
      line 93: 0
      line 94: 0
    LocalVariableTable:
      Start  Length  Slot  Name   Signature
          0       8     0  this   Lcom/example/Quux;

  public final java.lang.String getName();
    Code:
       0: aload_0
       1: getfield      #22                 // Field name:Ljava/lang/String;
       4: areturn
    LineNumberTable:
      line 85: 0
    LocalVariableTable:
      Start  Length  Slot  Name   Signature
          0       5     0  this   Lcom/example/Quux;

  public com.example.Quux(java.lang.String);
    Code:
       0: aload_1
       1: ldc           #24                 // String name
       3: invokestatic  #30                 // Method kotlin/jvm/internal/Intrinsics.checkParameterIsNotNull:(Ljava/lang/Object;Ljava/lang/String;)V
       6: aload_0
       7: invokespecial #31                 // Method java/lang/Object."<init>":()V
      10: aload_0
      11: aload_1
      12: putfield      #22                 // Field name:Ljava/lang/String;
      15: return
    LineNumberTable:
      line 85: 6
    LocalVariableTable:
      Start  Length  Slot  Name   Signature
          0      16     0  this   Lcom/example/Quux;
          0      16     1  name   Ljava/lang/String;

  public com.example.Quux(com.example.Qux);
    Code:
       0: aload_1
       1: ldc           #34                 // String q
       3: invokestatic  #30                 // Method kotlin/jvm/internal/Intrinsics.checkParameterIsNotNull:(Ljava/lang/Object;Ljava/lang/String;)V
       6: aload_0
       7: aload_1
       8: invokevirtual #39                 // Method com/example/Qux.getProp:()Ljava/lang/String;
      11: invokespecial #41                 // Method "<init>":(Ljava/lang/String;)V
      14: return
    LineNumberTable:
      line 87: 6
    LocalVariableTable:
      Start  Length  Slot  Name   Signature
          0      15     0  this   Lcom/example/Quux;
          0      15     1     q   Lcom/example/Qux;
}

build/classes/main/com/example/Qux$Companion$garply$1$Inner.class
Compiled from "KotlinFile.kt"
public final class com.example.Qux$Companion$garply$1$Inner {
  private final java.lang.String str;

  final com.example.Qux$Companion$garply$1 this$0;

  public final java.lang.String getStr();
    Code:
       0: aload_0
       1: getfield      #11                 // Field str:Ljava/lang/String;
       4: areturn
    LineNumberTable:
      line 73: 0
    LocalVariableTable:
      Start  Length  Slot  Name   Signature
          0       5     0  this   Lcom/example/Qux$Companion$garply$1$Inner;

  public com.example.Qux$Companion$garply$1$Inner();
    Code:
       0: aload_0
       1: aload_1
       2: putfield      #19                 // Field this$0:Lcom/example/Qux$Companion$garply$1;
       5: aload_0
       6: invokespecial #22                 // Method java/lang/Object."<init>":()V
       9: aload_0
      10: aload_1
      11: invokevirtual #27                 // Method com/example/Qux$Companion$garply$1.getWaldo:()Ljava/lang/String;
      14: putfield      #11                 // Field str:Ljava/lang/String;
      17: return
    LineNumberTable:
      line 72: 0
      line 73: 9
    LocalVariableTable:
      Start  Length  Slot  Name   Signature
          0      18     0  this   Lcom/example/Qux$Companion$garply$1$Inner;
          0      18     1 $outer   Lcom/example/Qux$Companion$garply$1;
}

build/classes/main/com/example/Qux$Companion$garply$1.class
Compiled from "KotlinFile.kt"
public final class com.example.Qux$Companion$garply$1 implements com.example.Garply {
  private final java.lang.String waldo;

  final com.example.Quux $q;

  public java.lang.String getWaldo();
    Code:
       0: aload_0
       1: getfield      #19                 // Field waldo:Ljava/lang/String;
       4: areturn
    LineNumberTable:
      line 71: 0
    LocalVariableTable:
      Start  Length  Slot  Name   Signature
          0       5     0  this   Lcom/example/Qux$Companion$garply$1;

  com.example.Qux$Companion$garply$1(com.example.Quux);
    Code:
       0: aload_0
       1: aload_1
       2: putfield      #27                 // Field $q:Lcom/example/Quux;
       5: aload_0
       6: invokespecial #30                 // Method java/lang/Object."<init>":()V
       9: aload_0
      10: aload_1
      11: invokevirtual #35                 // Method com/example/Quux.getName:()Ljava/lang/String;
      14: putfield      #19                 // Field waldo:Ljava/lang/String;
      17: return
    LineNumberTable:
      line 70: 0
      line 71: 9
    LocalVariableTable:
      Start  Length  Slot  Name   Signature
          0      18     0  this   Lcom/example/Qux$Companion$garply$1;
          0      18     1 $captured_local_variable$0   Lcom/example/Quux;

  public com.example.Quux lorem(com.example.Qux);
    Code:
       0: aload_1
       1: ldc           #40                 // String q
       3: invokestatic  #46                 // Method kotlin/jvm/internal/Intrinsics.checkParameterIsNotNull:(Ljava/lang/Object;Ljava/lang/String;)V
       6: aload_0
       7: aload_1
       8: invokestatic  #51                 // Method com/example/Garply$DefaultImpls.lorem:(Lcom/example/Garply;Lcom/example/Qux;)Lcom/example/Quux;
      11: areturn
    LineNumberTable:
      line 70: 6
    LocalVariableTable:
      Start  Length  Slot  Name   Signature
          0      12     0  this   Lcom/example/Garply;
          0      12     1     q   Lcom/example/Qux;

  public int getDp();
    Code:
       0: aload_0
       1: invokestatic  #58                 // Method com/example/Garply$DefaultImpls.getDp:(Lcom/example/Garply;)I
       4: ireturn
    LineNumberTable:
      line 70: 0
    LocalVariableTable:
      Start  Length  Slot  Name   Signature
          0       5     0  this   Lcom/example/Garply;
}

build/classes/main/com/example/Qux$Companion$WhenMappings.class
public final class com.example.Qux$Companion$WhenMappings {
  public static final int[] $EnumSwitchMapping$0;

  static {};
    Code:
       0: invokestatic  #14                 // Method com/example/Bool.values:()[Lcom/example/Bool;
       3: arraylength
       4: newarray       int
       6: putstatic     #16                 // Field $EnumSwitchMapping$0:[I
       9: getstatic     #16                 // Field $EnumSwitchMapping$0:[I
      12: getstatic     #20                 // Field com/example/Bool.OK:Lcom/example/Bool;
      15: invokevirtual #24                 // Method com/example/Bool.ordinal:()I
      18: iconst_1
      19: iastore
      20: getstatic     #16                 // Field $EnumSwitchMapping$0:[I
      23: getstatic     #27                 // Field com/example/Bool.NG:Lcom/example/Bool;
      26: invokevirtual #24                 // Method com/example/Bool.ordinal:()I
      29: iconst_2
      30: iastore
      31: return
}

build/classes/main/com/example/Qux$Companion.class
Compiled from "KotlinFile.kt"
public final class com.example.Qux$Companion {
  public final int add(com.example.Qux, com.example.Quux);
    Code:
       0: aload_1
       1: ldc           #11                 // String q
       3: invokestatic  #17                 // Method kotlin/jvm/internal/Intrinsics.checkParameterIsNotNull:(Ljava/lang/Object;Ljava/lang/String;)V
       6: aload_2
       7: ldc           #19                 // String qx
       9: invokestatic  #17                 // Method kotlin/jvm/internal/Intrinsics.checkParameterIsNotNull:(Ljava/lang/Object;Ljava/lang/String;)V
      12: aload_1
      13: invokevirtual #25                 // Method com/example/Qux.getProp:()Ljava/lang/String;
      16: invokevirtual #31                 // Method java/lang/String.length:()I
      19: aload_2
      20: invokevirtual #36                 // Method com/example/Quux.getName:()Ljava/lang/String;
      23: invokevirtual #31                 // Method java/lang/String.length:()I
      26: iadd
      27: ireturn
    LineNumberTable:
      line 68: 12
    LocalVariableTable:
      Start  Length  Slot  Name   Signature
          0      28     0  this   Lcom/example/Qux$Companion;
          0      28     1     q   Lcom/example/Qux;
          0      28     2    qx   Lcom/example/Quux;

  public final com.example.Garply garply(com.example.Quux);
    Code:
       0: aload_1
       1: ldc           #11                 // String q
       3: invokestatic  #17                 // Method kotlin/jvm/internal/Intrinsics.checkParameterIsNotNull:(Ljava/lang/Object;Ljava/lang/String;)V
       6: new           #44                 // class com/example/Qux$Companion$garply$1
       9: dup
      10: aload_1
      11: invokespecial #48                 // Method com/example/Qux$Companion$garply$1."<init>":(Lcom/example/Quux;)V
      14: checkcast     #50                 // class com/example/Garply
      17: areturn
    LineNumberTable:
      line 70: 6
      line 75: 17
    LocalVariableTable:
      Start  Length  Slot  Name   Signature
          0      18     0  this   Lcom/example/Qux$Companion;
          0      18     1     q   Lcom/example/Quux;

  public final java.lang.String boolean(com.example.Bool);
    Code:
       0: aload_1
       1: ldc           #54                 // String b
       3: invokestatic  #17                 // Method kotlin/jvm/internal/Intrinsics.checkParameterIsNotNull:(Ljava/lang/Object;Ljava/lang/String;)V
       6: aload_1
       7: getstatic     #60                 // Field com/example/Qux$Companion$WhenMappings.$EnumSwitchMapping$0:[I
      10: swap
      11: invokevirtual #65                 // Method com/example/Bool.ordinal:()I
      14: iaload
      15: lookupswitch  { // 2
                     1: 40
                     2: 45
               default: 50
          }
      40: ldc           #67                 // String true
      42: goto          58
      45: ldc           #69                 // String false
      47: goto          58
      50: new           #71                 // class kotlin/NoWhenBranchMatchedException
      53: dup
      54: invokespecial #74                 // Method kotlin/NoWhenBranchMatchedException."<init>":()V
      57: athrow
      58: areturn
    LineNumberTable:
      line 77: 6
      line 78: 40
      line 79: 45
      line 77: 58
      line 80: 58
    LocalVariableTable:
      Start  Length  Slot  Name   Signature
          0      59     0  this   Lcom/example/Qux$Companion;
          0      59     1     b   Lcom/example/Bool;

  private com.example.Qux$Companion();
    Code:
       0: aload_0
       1: invokespecial #76                 // Method java/lang/Object."<init>":()V
       4: return
    LineNumberTable:
      line 65: 0
    LocalVariableTable:
      Start  Length  Slot  Name   Signature
          0       5     0  this   Lcom/example/Qux$Companion;

  public com.example.Qux$Companion(kotlin.jvm.internal.DefaultConstructorMarker);
    Code:
       0: aload_0
       1: invokespecial #78                 // Method "<init>":()V
       4: return
    LineNumberTable:
      line 65: 0
    LocalVariableTable:
      Start  Length  Slot  Name   Signature
          0       5     0  this   Lcom/example/Qux$Companion;
          0       5     1 $constructor_marker   Lkotlin/jvm/internal/DefaultConstructorMarker;
}

build/classes/main/com/example/Qux$Inner$InChild.class
Compiled from "KotlinFile.kt"
public final class com.example.Qux$Inner$InChild {
  final com.example.Qux$Inner this$0;

  public final int value();
    Code:
       0: aload_0
       1: getfield      #10                 // Field this$0:Lcom/example/Qux$Inner;
       4: invokevirtual #15                 // Method com/example/Qux$Inner.getValue:()I
       7: ireturn
    LineNumberTable:
      line 60: 0
    LocalVariableTable:
      Start  Length  Slot  Name   Signature
          0       8     0  this   Lcom/example/Qux$Inner$InChild;

  public com.example.Qux$Inner$InChild();
    Code:
       0: aload_0
       1: aload_1
       2: putfield      #10                 // Field this$0:Lcom/example/Qux$Inner;
       5: aload_0
       6: invokespecial #22                 // Method java/lang/Object."<init>":()V
       9: return
    LineNumberTable:
      line 59: 0
    LocalVariableTable:
      Start  Length  Slot  Name   Signature
          0      10     0  this   Lcom/example/Qux$Inner$InChild;
          0      10     1 $outer   Lcom/example/Qux$Inner;
}

build/classes/main/com/example/Qux$Inner.class
Compiled from "KotlinFile.kt"
public final class com.example.Qux$Inner {
  private final int inner;

  private final int value;

  final com.example.Qux this$0;

  public final int getInner();
    Code:
       0: aload_0
       1: getfield      #11                 // Field inner:I
       4: ireturn
    LineNumberTable:
      line 57: 0
    LocalVariableTable:
      Start  Length  Slot  Name   Signature
          0       5     0  this   Lcom/example/Qux$Inner;

  public final int inner();
    Code:
       0: aload_0
       1: getfield      #16                 // Field value:I
       4: iconst_2
       5: imul
       6: ireturn
    LineNumberTable:
      line 58: 0
    LocalVariableTable:
      Start  Length  Slot  Name   Signature
          0       7     0  this   Lcom/example/Qux$Inner;

  public final int getValue();
    Code:
       0: aload_0
       1: getfield      #16                 // Field value:I
       4: ireturn
    LineNumberTable:
      line 56: 0
    LocalVariableTable:
      Start  Length  Slot  Name   Signature
          0       5     0  this   Lcom/example/Qux$Inner;

  public com.example.Qux$Inner(int);
    Code:
       0: aload_0
       1: aload_1
       2: putfield      #23                 // Field this$0:Lcom/example/Qux;
       5: aload_0
       6: invokespecial #26                 // Method java/lang/Object."<init>":()V
       9: aload_0
      10: iload_2
      11: putfield      #16                 // Field value:I
      14: aload_0
      15: aload_0
      16: getfield      #16                 // Field value:I
      19: iconst_2
      20: imul
      21: putfield      #11                 // Field inner:I
      24: return
    LineNumberTable:
      line 56: 0
      line 57: 14
    LocalVariableTable:
      Start  Length  Slot  Name   Signature
          0      25     0  this   Lcom/example/Qux$Inner;
          0      25     1 $outer   Lcom/example/Qux;
          0      25     2 value   I
}

build/classes/main/com/example/Qux$WhenMappings.class
public final class com.example.Qux$WhenMappings {
  public static final int[] $EnumSwitchMapping$0;

  static {};
    Code:
       0: invokestatic  #14                 // Method com/example/Bool.values:()[Lcom/example/Bool;
       3: arraylength
       4: newarray       int
       6: putstatic     #16                 // Field $EnumSwitchMapping$0:[I
       9: getstatic     #16                 // Field $EnumSwitchMapping$0:[I
      12: getstatic     #20                 // Field com/example/Bool.OK:Lcom/example/Bool;
      15: invokevirtual #24                 // Method com/example/Bool.ordinal:()I
      18: iconst_1
      19: iastore
      20: getstatic     #16                 // Field $EnumSwitchMapping$0:[I
      23: getstatic     #27                 // Field com/example/Bool.NG:Lcom/example/Bool;
      26: invokevirtual #24                 // Method com/example/Bool.ordinal:()I
      29: iconst_2
      30: iastore
      31: return
}

build/classes/main/com/example/Qux.class
Compiled from "KotlinFile.kt"
public final class com.example.Qux {
  private final java.lang.String prop;

  public static final com.example.Qux$Companion Companion;

  public static void prop$annotations();
    Code:
       0: return

  public final java.lang.String getProp();
    Code:
       0: aload_0
       1: getfield      #16                 // Field prop:Ljava/lang/String;
       4: areturn
    LineNumberTable:
      line 31: 0
    LocalVariableTable:
      Start  Length  Slot  Name   Signature
          0       5     0  this   Lcom/example/Qux;

  public final java.util.List<java.lang.String> function(int, java.lang.String);
    Code:
       0: aload_2
       1: ldc           #22                 // String msg
       3: invokestatic  #28                 // Method kotlin/jvm/internal/Intrinsics.checkParameterIsNotNull:(Ljava/lang/Object;Ljava/lang/String;)V
       6: iload_1
       7: iconst_0
       8: if_icmpge     17
      11: invokestatic  #34                 // Method kotlin/collections/CollectionsKt.emptyList:()Ljava/util/List;
      14: goto          128
      17: iconst_1
      18: new           #36                 // class kotlin/ranges/IntRange
      21: dup_x1
      22: swap
      23: iload_1
      24: invokespecial #40                 // Method kotlin/ranges/IntRange."<init>":(II)V
      27: checkcast     #42                 // class java/lang/Iterable
      30: astore_3
      31: aload_3
      32: astore        4
      34: new           #44                 // class java/util/ArrayList
      37: dup
      38: aload_3
      39: bipush        10
      41: invokestatic  #48                 // Method kotlin/collections/CollectionsKt.collectionSizeOrDefault:(Ljava/lang/Iterable;I)I
      44: invokespecial #51                 // Method java/util/ArrayList."<init>":(I)V
      47: checkcast     #53                 // class java/util/Collection
      50: astore        5
      52: aload         4
      54: invokeinterface #57,  1           // InterfaceMethod java/lang/Iterable.iterator:()Ljava/util/Iterator;
      59: astore        6
      61: aload         6
      63: invokeinterface #63,  1           // InterfaceMethod java/util/Iterator.hasNext:()Z
      68: ifeq          123
      71: aload         6
      73: checkcast     #65                 // class kotlin/collections/IntIterator
      76: invokevirtual #69                 // Method kotlin/collections/IntIterator.nextInt:()I
      79: istore        7
      81: aload         5
      83: iload         7
      85: istore        8
      87: astore        12
      89: new           #71                 // class java/lang/StringBuilder
      92: dup
      93: invokespecial #73                 // Method java/lang/StringBuilder."<init>":()V
      96: aload_2
      97: invokevirtual #77                 // Method java/lang/StringBuilder.append:(Ljava/lang/String;)Ljava/lang/StringBuilder;
     100: iload         8
     102: invokevirtual #80                 // Method java/lang/StringBuilder.append:(I)Ljava/lang/StringBuilder;
     105: invokevirtual #83                 // Method java/lang/StringBuilder.toString:()Ljava/lang/String;
     108: astore        13
     110: aload         12
     112: aload         13
     114: invokeinterface #87,  2           // InterfaceMethod java/util/Collection.add:(Ljava/lang/Object;)Z
     119: pop
     120: goto          61
     123: aload         5
     125: checkcast     #89                 // class java/util/List
     128: areturn
    LineNumberTable:
      line 34: 6
      line 216: 31
      line 217: 52
      line 218: 81
      line 34: 89
      line 217: 120
      line 219: 123
      line 34: 128
    LocalVariableTable:
      Start  Length  Slot  Name   Signature
         89      19     8    it   I
         89      19     9 $i$a$1$map   I
         81      39     7 item$iv$iv   I
         52      73     4 $receiver$iv$iv   Ljava/lang/Iterable;
         52      73     5 destination$iv$iv   Ljava/util/Collection;
         52      73    10 $i$f$mapTo   I
         31      97     3 $receiver$iv   Ljava/lang/Iterable;
         31      97    11 $i$f$map   I
          0     129     0  this   Lcom/example/Qux;
          0     129     1     t   I
          0     129     2   msg   Ljava/lang/String;

  public final <R extends java.io.Closeable> void tryAndClose(R, kotlin.jvm.functions.Function1<? super R, kotlin.Unit>);
    Code:
       0: aload_1
       1: ldc           #107                // String $receiver
       3: invokestatic  #28                 // Method kotlin/jvm/internal/Intrinsics.checkParameterIsNotNull:(Ljava/lang/Object;Ljava/lang/String;)V
       6: aload_2
       7: ldc           #109                // String action
       9: invokestatic  #28                 // Method kotlin/jvm/internal/Intrinsics.checkParameterIsNotNull:(Ljava/lang/Object;Ljava/lang/String;)V
      12: nop
      13: aload_2
      14: aload_1
      15: invokeinterface #115,  2          // InterfaceMethod kotlin/jvm/functions/Function1.invoke:(Ljava/lang/Object;)Ljava/lang/Object;
      20: pop
      21: aload_1
      22: invokeinterface #120,  1          // InterfaceMethod java/io/Closeable.close:()V
      27: goto          39
      30: astore_3
      31: aload_1
      32: invokeinterface #120,  1          // InterfaceMethod java/io/Closeable.close:()V
      37: aload_3
      38: athrow
      39: return
    Exception table:
       from    to  target type
          12    21    30   any
          30    31    30   any
    LineNumberTable:
      line 37: 12
      line 38: 13
      line 40: 21
      line 41: 39
      line 42: 39
    LocalVariableTable:
      Start  Length  Slot  Name   Signature
          0      40     0  this   Lcom/example/Qux;
          0      40     1 $receiver   Ljava/io/Closeable;
          0      40     2 action   Lkotlin/jvm/functions/Function1;

  public static void id$annotations(com.example.Quux);
    Code:
       0: return

  public final java.lang.String getId(com.example.Quux);
    Code:
       0: aload_1
       1: ldc           #107                // String $receiver
       3: invokestatic  #28                 // Method kotlin/jvm/internal/Intrinsics.checkParameterIsNotNull:(Ljava/lang/Object;Ljava/lang/String;)V
       6: aload_1
       7: invokevirtual #133                // Method com/example/Quux.getName:()Ljava/lang/String;
      10: areturn
    LineNumberTable:
      line 46: 6
    LocalVariableTable:
      Start  Length  Slot  Name   Signature
          0      11     0  this   Lcom/example/Qux;
          0      11     1 $receiver   Lcom/example/Quux;

  public final java.lang.String foop(com.example.Qux);
    Code:
       0: aload_1
       1: ldc           #107                // String $receiver
       3: invokestatic  #28                 // Method kotlin/jvm/internal/Intrinsics.checkParameterIsNotNull:(Ljava/lang/Object;Ljava/lang/String;)V
       6: aload_1
       7: getfield      #16                 // Field prop:Ljava/lang/String;
      10: new           #71                 // class java/lang/StringBuilder
      13: dup
      14: invokespecial #73                 // Method java/lang/StringBuilder."<init>":()V
      17: swap
      18: invokevirtual #77                 // Method java/lang/StringBuilder.append:(Ljava/lang/String;)Ljava/lang/StringBuilder;
      21: aload_1
      22: invokevirtual #137                // Method toString:()Ljava/lang/String;
      25: invokevirtual #77                 // Method java/lang/StringBuilder.append:(Ljava/lang/String;)Ljava/lang/StringBuilder;
      28: invokevirtual #83                 // Method java/lang/StringBuilder.toString:()Ljava/lang/String;
      31: areturn
    LineNumberTable:
      line 48: 6
    LocalVariableTable:
      Start  Length  Slot  Name   Signature
          0      32     0  this   Lcom/example/Qux;
          0      32     1 $receiver   Lcom/example/Qux;

  public final boolean bool(com.example.Bool);
    Code:
       0: aload_1
       1: ldc           #141                // String b
       3: invokestatic  #28                 // Method kotlin/jvm/internal/Intrinsics.checkParameterIsNotNull:(Ljava/lang/Object;Ljava/lang/String;)V
       6: aload_1
       7: getstatic     #147                // Field com/example/Qux$WhenMappings.$EnumSwitchMapping$0:[I
      10: swap
      11: invokevirtual #152                // Method com/example/Bool.ordinal:()I
      14: iaload
      15: lookupswitch  { // 2
                     1: 40
                     2: 44
               default: 48
          }
      40: iconst_1
      41: goto          56
      44: iconst_0
      45: goto          56
      48: new           #154                // class kotlin/NoWhenBranchMatchedException
      51: dup
      52: invokespecial #155                // Method kotlin/NoWhenBranchMatchedException."<init>":()V
      55: athrow
      56: ireturn
    LineNumberTable:
      line 50: 6
      line 51: 40
      line 52: 44
      line 50: 56
      line 53: 56
    LocalVariableTable:
      Start  Length  Slot  Name   Signature
          0      57     0  this   Lcom/example/Qux;
          0      57     1     b   Lcom/example/Bool;

  public com.example.Qux();
    Code:
       0: aload_0
       1: invokespecial #157                // Method java/lang/Object."<init>":()V
       4: aload_0
       5: ldc           #9                  // String ooo
       7: putfield      #16                 // Field prop:Ljava/lang/String;
      10: return
    LineNumberTable:
      line 29: 0
      line 31: 4
    LocalVariableTable:
      Start  Length  Slot  Name   Signature
          0      11     0  this   Lcom/example/Qux;

  static {};
    Code:
       0: new           #186                // class com/example/Qux$Companion
       3: dup
       4: aconst_null
       5: invokespecial #191                // Method com/example/Qux$Companion."<init>":(Lkotlin/jvm/internal/DefaultConstructorMarker;)V
       8: putstatic     #184                // Field Companion:Lcom/example/Qux$Companion;
      11: return

  public static final int add(com.example.Qux, com.example.Quux);
    Code:
       0: aload_0
       1: ldc           #180                // String q
       3: invokestatic  #28                 // Method kotlin/jvm/internal/Intrinsics.checkParameterIsNotNull:(Ljava/lang/Object;Ljava/lang/String;)V
       6: aload_1
       7: ldc           #182                // String qx
       9: invokestatic  #28                 // Method kotlin/jvm/internal/Intrinsics.checkParameterIsNotNull:(Ljava/lang/Object;Ljava/lang/String;)V
      12: getstatic     #184                // Field Companion:Lcom/example/Qux$Companion;
      15: aload_0
      16: aload_1
      17: invokevirtual #188                // Method com/example/Qux$Companion.add:(Lcom/example/Qux;Lcom/example/Quux;)I
      20: ireturn
    LocalVariableTable:
      Start  Length  Slot  Name   Signature
          0      21     0     q   Lcom/example/Qux;
          0      21     1    qx   Lcom/example/Quux;
}

build/classes/main/com/example/Sealed$SealedNested.class
Compiled from "KotlinFile.kt"
public final class com.example.Sealed$SealedNested {
  public com.example.Sealed$SealedNested();
    Code:
       0: aload_0
       1: invokespecial #9                  // Method java/lang/Object."<init>":()V
       4: return
    LineNumberTable:
      line 196: 0
    LocalVariableTable:
      Start  Length  Slot  Name   Signature
          0       5     0  this   Lcom/example/Sealed$SealedNested;
}

build/classes/main/com/example/Sealed.class
Compiled from "KotlinFile.kt"
public abstract class com.example.Sealed {
  private final int sealedValue;

  public static void sealedValue$annotations();
    Code:
       0: return

  public final int getSealedValue();
    Code:
       0: aload_0
       1: getfield      #14                 // Field sealedValue:I
       4: ireturn
    LineNumberTable:
      line 194: 0
    LocalVariableTable:
      Start  Length  Slot  Name   Signature
          0       5     0  this   Lcom/example/Sealed;

  private com.example.Sealed();
    Code:
       0: aload_0
       1: invokespecial #19                 // Method java/lang/Object."<init>":()V
       4: return
    LineNumberTable:
      line 192: 0
    LocalVariableTable:
      Start  Length  Slot  Name   Signature
          0       5     0  this   Lcom/example/Sealed;

  public com.example.Sealed(kotlin.jvm.internal.DefaultConstructorMarker);
    Code:
       0: aload_0
       1: invokespecial #21                 // Method "<init>":()V
       4: return
    LineNumberTable:
      line 192: 0
    LocalVariableTable:
      Start  Length  Slot  Name   Signature
          0       5     0  this   Lcom/example/Sealed;
          0       5     1 $constructor_marker   Lkotlin/jvm/internal/DefaultConstructorMarker;
}

build/classes/main/com/example/Vip$Most.class
Compiled from "KotlinFile.kt"
public final class com.example.Vip$Most {
  public com.example.Vip$Most();
    Code:
       0: aload_0
       1: invokespecial #9                  // Method java/lang/Object."<init>":()V
       4: return
    LineNumberTable:
      line 145: 0
    LocalVariableTable:
      Start  Length  Slot  Name   Signature
          0       5     0  this   Lcom/example/Vip$Most;
}

build/classes/main/com/example/Vip.class
Compiled from "KotlinFile.kt"
public final class com.example.Vip {
  private static final com.example.Vip vip;

  public static final com.example.Vip INSTANCE;

  public static void vip$annotations();
    Code:
       0: return

  public final com.example.Vip getVip();
    Code:
       0: getstatic     #14                 // Field vip:Lcom/example/Vip;
       3: areturn
    LineNumberTable:
      line 141: 0
    LocalVariableTable:
      Start  Length  Slot  Name   Signature
          0       4     0  this   Lcom/example/Vip;

  public final com.example.Vip vip();
    Code:
       0: aload_0
       1: areturn
    LineNumberTable:
      line 143: 0
    LocalVariableTable:
      Start  Length  Slot  Name   Signature
          0       2     0  this   Lcom/example/Vip;

  private com.example.Vip();
    Code:
       0: aload_0
       1: invokespecial #18                 // Method java/lang/Object."<init>":()V
       4: aload_0
       5: checkcast     #2                  // class com/example/Vip
       8: putstatic     #21                 // Field INSTANCE:Lcom/example/Vip;
      11: aload_0
      12: checkcast     #2                  // class com/example/Vip
      15: putstatic     #14                 // Field vip:Lcom/example/Vip;
      18: return
    LineNumberTable:
      line 139: 0
      line 141: 11
    LocalVariableTable:
      Start  Length  Slot  Name   Signature
          0      19     0  this   Lcom/example/Vip;

  static {};
    Code:
       0: new           #2                  // class com/example/Vip
       3: invokespecial #36                 // Method "<init>":()V
       6: return
    LineNumberTable:
      line 139: 0
}
